satchip/__init__.py
satchip/chip_data.py
satchip/chip_hls.py
satchip/chip_hyp3s1rtc.py
satchip/chip_label.py
satchip/chip_operas1rtc.py
satchip/chip_sentinel2.py
satchip/chip_view.py
satchip/chip_xr_base.py
satchip/major_tom_grid.py
satchip/terra_mind_grid.py
satchip/utils.py
satchip-0.6.1.dist-info/licenses/LICENSE
satchip-0.6.1.dist-info/METADATA
satchip-0.6.1.dist-info/WHEEL
satchip-0.6.1.dist-info/entry_points.txt
satchip-0.6.1.dist-info/top_level.txt
satchip-0.6.1.dist-info/RECORD
