Metadata-Version: 2.4
Name: satchip
Version: 0.6.1
Summary: A package for satellite image AI data prep
Author-email: forrestfwilliams <ffwilliams2@alaska.edu>
License: BSD-3-Clause
Project-URL: Homepage, https://github.com/forrestfwilliams/satchip
Project-URL: Documentation, https://github.com/forrestfwilliams/satchip
Classifier: Intended Audience :: Science/Research
Classifier: License :: OSI Approved :: BSD License
Classifier: Natural Language :: English
Classifier: Operating System :: OS Independent
Classifier: Programming Language :: Python :: 3
Classifier: Programming Language :: Python :: 3.10
Classifier: Programming Language :: Python :: 3.11
Classifier: Programming Language :: Python :: 3.12
Classifier: Programming Language :: Python :: 3.13
Requires-Python: >=3.11
License-File: LICENSE
Requires-Dist: gdal
Requires-Dist: numpy
Requires-Dist: shapely
Requires-Dist: pyproj
Requires-Dist: pystac-client
Requires-Dist: rasterio
Requires-Dist: zarr>=3
Requires-Dist: xarray
Requires-Dist: rioxarray
Requires-Dist: pandas
Requires-Dist: geopandas
Requires-Dist: asf_search
Requires-Dist: earthaccess
Requires-Dist: hyp3_sdk
Requires-Dist: tqdm
Requires-Dist: matplotlib
Provides-Extra: develop
Requires-Dist: mypy; extra == "develop"
Requires-Dist: ruff; extra == "develop"
Requires-Dist: pytest; extra == "develop"
Requires-Dist: pytest-console-scripts; extra == "develop"
Requires-Dist: pytest-cov; extra == "develop"
Dynamic: license-file
